{
  "$schema": "https://biomejs.dev/schemas/1.5.3/schema.json",
  "organizeImports": {
    "enabled": true
  },
  "linter": {
    "enabled": true,
    "rules": {
      "recommended": true,
      "complexity": {
        "noExtraBooleanCast": "error",
        "noMultipleSpacesInRegularExpressionLiterals": "error",
        "noUselessCatch": "error",
        "noUselessTypeConstraint": "error",
        "noWith": "error"
      },
      "correctness": {
        "noUnusedVariables": "error"
      },
      "style": {
        "noParameterAssign": "error"
      },
      "suspicious": {
        "noAssignInExpressions": "error",
        "noArrayIndexKey": "warn",
        "noCommentText": "error"
      }
    }
  },
  "formatter": {
    "enabled": true,
    "indentStyle": "space",
    "indentWidth": 2,
    "lineWidth": 100
  },
  "javascript": {
    "formatter": {
      "quoteStyle": "single",
      "trailingCommas": "es5",
      "semicolons": "always"
    }
  }
}

